datasmryzr/__about__.py
datasmryzr/__init__.py
datasmryzr/annotate.py
datasmryzr/clusters.py
datasmryzr/core_genome.py
datasmryzr/datasmryzr.py
datasmryzr/distances.py
datasmryzr/pangenome.py
datasmryzr/smryz.py
datasmryzr/summary.py
datasmryzr/tables.py
datasmryzr/tree.py
datasmryzr/utils.py
datasmryzr/templates/base_config.json
datasmryzr/templates/report.html.j2
datasmryzr-0.1.1.dist-info/METADATA
datasmryzr-0.1.1.dist-info/WHEEL
datasmryzr-0.1.1.dist-info/entry_points.txt
datasmryzr-0.1.1.dist-info/licenses/LICENSE.txt
datasmryzr-0.1.1.dist-info/RECORD
