Metadata-Version: 2.4
Name: datasmryzr
Version: 0.1.1
Project-URL: Documentation, https://github.com/kristyhoran/datasmryzr#readme
Project-URL: Issues, https://github.com/kristyhoran/datasmryzr/issues
Project-URL: Source, https://github.com/kristyhoran/datasmryzr
Author-email: Kristy Horan <kristyhoran15@gmail.com>
License-Expression: MIT
License-File: LICENSE.txt
Classifier: Development Status :: 4 - Beta
Classifier: Programming Language :: Python
Classifier: Programming Language :: Python :: 3.10
Classifier: Programming Language :: Python :: 3.11
Classifier: Programming Language :: Python :: 3.12
Classifier: Programming Language :: Python :: Implementation :: CPython
Classifier: Programming Language :: Python :: Implementation :: PyPy
Requires-Python: >=3.10
Requires-Dist: altair
Requires-Dist: biopython
Requires-Dist: click
Requires-Dist: jinja2
Requires-Dist: mycolorpy
Requires-Dist: numpy
Requires-Dist: pandas
